vcrpy_bincon/__init__.py
vcrpy_bincon/_version.py
vcrpy_bincon/converter.py
vcrpy_bincon/py.typed
vcrpy_bincon-0.3.0.dist-info/licenses/LICENSE
vcrpy_bincon-0.3.0.dist-info/METADATA
vcrpy_bincon-0.3.0.dist-info/WHEEL
vcrpy_bincon-0.3.0.dist-info/entry_points.txt
vcrpy_bincon-0.3.0.dist-info/top_level.txt
vcrpy_bincon-0.3.0.dist-info/RECORD
